bits/__init__.py
bits/ccure/__init__.py
bits/ccure/update.py
bits_ccure-1.0.10.dist-info/METADATA
bits_ccure-1.0.10.dist-info/WHEEL
bits_ccure-1.0.10.dist-info/top_level.txt
bits_ccure-1.0.10.dist-info/RECORD
