Metadata-Version: 2.1
Name: bits-ccure
Version: 1.0.10
Summary: BITS CCURE
Author: Lukas Karlsson
Author-email: karlsson@broadinstitute.org
License: Apache Software License
Platform: UNKNOWN
